{
  "$schema": "vscode://schemas/color-theme",
  "name": "3BX Dark",
  "type": "dark",
  "author": "3BX Team",
  "semanticClass": "theme.dark.3bx",
  "semanticHighlighting": true,
  "include": "./base-dark.json",
  "tokenColors": [
    {
      "name": "Comments",
      "scope": "comment, comment.line.number-sign.3bx",
      "settings": {
        "foreground": "#6A9955",
        "fontStyle": "italic"
      }
    },
    {
      "name": "Strings",
      "scope": "string, string.quoted.double.3bx",
      "settings": {
        "foreground": "#CE9178"
      }
    },
    {
      "name": "Import paths",
      "scope": "string.unquoted.import-path.3bx",
      "settings": {
        "foreground": "#D7BA7D"
      }
    },
    {
      "name": "Escape characters",
      "scope": "constant.character.escape.3bx",
      "settings": {
        "foreground": "#D7BA7D"
      }
    },
    {
      "name": "Numbers",
      "scope": "constant.numeric, constant.numeric.integer.3bx, constant.numeric.float.3bx",
      "settings": {
        "foreground": "#B5CEA8"
      }
    },
    {
      "name": "Constants (UPPER_CASE)",
      "scope": "constant.other.3bx",
      "settings": {
        "foreground": "#4FC1FF"
      }
    },
    {
      "name": "Pattern type keywords (effect, expression, section, condition)",
      "scope": "storage.type.effect.3bx, storage.type.expression.3bx, storage.type.section.3bx, storage.type.condition.3bx, storage.type.pattern.3bx",
      "settings": {
        "foreground": "#C586C0",
        "fontStyle": "bold"
      }
    },
    {
      "name": "Control flow keywords",
      "scope": "keyword.control.3bx, keyword.control.when.3bx, keyword.control.triggered.3bx, keyword.control.parsed.3bx, keyword.control.get.3bx, keyword.control.set.3bx, keyword.control.import.3bx",
      "settings": {
        "foreground": "#C586C0"
      }
    },
    {
      "name": "Assignment keyword (set)",
      "scope": "keyword.operator.assignment.3bx",
      "settings": {
        "foreground": "#569CD6"
      }
    },
    {
      "name": "Pattern-related keywords",
      "scope": "keyword.other.pattern.3bx, keyword.other.syntax.3bx, keyword.other.priority.3bx",
      "settings": {
        "foreground": "#9CDCFE"
      }
    },
    {
      "name": "Boolean/logical operators",
      "scope": "keyword.operator.logical.3bx",
      "settings": {
        "foreground": "#569CD6"
      }
    },
    {
      "name": "Article keywords (the, a, an)",
      "scope": "keyword.other.article.3bx",
      "settings": {
        "foreground": "#808080",
        "fontStyle": "italic"
      }
    },
    {
      "name": "Pattern literal keywords in definitions",
      "scope": "keyword.other.pattern-literal.3bx",
      "settings": {
        "foreground": "#DCDCAA"
      }
    },
    {
      "name": "Arithmetic operators",
      "scope": "keyword.operator.arithmetic.3bx",
      "settings": {
        "foreground": "#D4D4D4"
      }
    },
    {
      "name": "Comparison operators",
      "scope": "keyword.operator.comparison.3bx, keyword.operator.pattern.3bx",
      "settings": {
        "foreground": "#D4D4D4"
      }
    },
    {
      "name": "Intrinsic function (@intrinsic)",
      "scope": "support.function.builtin.intrinsic.3bx",
      "settings": {
        "foreground": "#4EC9B0",
        "fontStyle": "bold"
      }
    },
    {
      "name": "Intrinsic operation names",
      "scope": "support.constant.intrinsic-operation.3bx",
      "settings": {
        "foreground": "#4EC9B0"
      }
    },
    {
      "name": "Print builtin",
      "scope": "support.function.builtin.print.3bx",
      "settings": {
        "foreground": "#DCDCAA"
      }
    },
    {
      "name": "Pattern parameters",
      "scope": "variable.parameter.pattern.3bx, variable.parameter.lazy.3bx",
      "settings": {
        "foreground": "#9CDCFE",
        "fontStyle": "italic"
      }
    },
    {
      "name": "Regular variables",
      "scope": "variable.other.3bx",
      "settings": {
        "foreground": "#9CDCFE"
      }
    },
    {
      "name": "Private variables",
      "scope": "variable.other.private.3bx",
      "settings": {
        "foreground": "#7A7A7A"
      }
    },
    {
      "name": "Lazy expression braces",
      "scope": "punctuation.definition.lazy.begin.3bx, punctuation.definition.lazy.end.3bx",
      "settings": {
        "foreground": "#FFD700"
      }
    },
    {
      "name": "Lazy expression content",
      "scope": "meta.embedded.lazy.3bx",
      "settings": {
        "foreground": "#E0C080"
      }
    },
    {
      "name": "Punctuation",
      "scope": "punctuation.definition.block.3bx, punctuation.definition.pattern.3bx, punctuation.separator.comma.3bx",
      "settings": {
        "foreground": "#D4D4D4"
      }
    },
    {
      "name": "Brackets",
      "scope": "punctuation.bracket.round.3bx, punctuation.bracket.square.3bx, punctuation.definition.arguments.begin.3bx, punctuation.definition.arguments.end.3bx",
      "settings": {
        "foreground": "#FFD700"
      }
    }
  ],
  "colors": {
    "editor.background": "#1E1E1E",
    "editor.foreground": "#D4D4D4"
  }
}
